MANIFEST.in
setup.py
mrsh/__init__.py
mrsh.egg-info/PKG-INFO
mrsh.egg-info/SOURCES.txt
mrsh.egg-info/dependency_links.txt
mrsh.egg-info/not-zip-safe
mrsh.egg-info/requires.txt
mrsh.egg-info/top_level.txt
mrsh/logger/__init__.py
mrsh/logger/logger.py
mrsh/logger/logging.yaml
mrsh/mongo/__init__.py
mrsh/mongo/mongo.py
mrsh/mongo/affinity/__init__.py
mrsh/mongo/affinity/mongo_affinity.py
mrsh/mongo/chat/__init__.py
mrsh/mongo/chat/mongo_chat.py
mrsh/mongo/common/__init__.py
mrsh/mongo/common/mongo_common.py
mrsh/mongo/controller/__init__.py
mrsh/mongo/controller/mongo_controller.py
mrsh/mongo/factorizer/__init__.py
mrsh/mongo/factorizer/mongo_factorizer.py
mrsh/mongo/news_consumer/__init__.py
mrsh/mongo/news_consumer/mongo_news_consumer.py
mrsh/mongo/reccomender/__init__.py
mrsh/mongo/reccomender/mongo_reccomender.py
mrsh/mongo/social_worker/__init__.py
mrsh/mongo/social_worker/mongo_social_worker.py
mrsh/mongo/teacher/__init__.py
mrsh/mongo/teacher/mongo_teacher.py
mrsh/mongo/web_app/__init__.py
mrsh/mongo/web_app/mongo_web_app.py
mrsh/rabbit/__init__.py
mrsh/rabbit/rabbit.py
mrsh/rabbit/rabbit_setting.py
mrsh/rabbit/receiver.py
mrsh/rabbit/sender.py
mrsh/social/__init__.py
mrsh/social/social.py
mrsh/util/__init__.py
mrsh/util/util.py