Metadata-Version: 1.0
Name: mrsh
Version: 1.0.0.0
Summary: Core code for mrsh infrastructure
Home-page: http://packages.python.org/mrsh
Author: Gioacchino Bombaci
Author-email: gioakbombaci@gmail.com
License: GPL
Keywords: mrsh's core
Platform: UNKNOWN
